yolodetection/__init__.py
yolodetection/detector.py
detection_package-0.0.2.dist-info/METADATA
detection_package-0.0.2.dist-info/WHEEL
detection_package-0.0.2.dist-info/top_level.txt
detection_package-0.0.2.dist-info/RECORD
