Metadata-Version: 2.1
Name: detection-package
Version: 0.0.2
Requires-Dist: ultralytics ==8.0.54
